epub_sage/__init__.py
epub_sage/dublin_core_service.py
epub_sage/py.typed
epub_sage/cli/__init__.py
epub_sage/cli/utils.py
epub_sage/cli/commands/__init__.py
epub_sage/cli/commands/content.py
epub_sage/cli/commands/export.py
epub_sage/cli/commands/images.py
epub_sage/cli/commands/info.py
epub_sage/cli/commands/media.py
epub_sage/cli/commands/metadata.py
epub_sage/core/__init__.py
epub_sage/core/classification_patterns.py
epub_sage/core/content_classifier.py
epub_sage/core/dublin_core_parser.py
epub_sage/core/manifest_handler.py
epub_sage/core/metadata_element_parsers.py
epub_sage/core/nav_parser.py
epub_sage/core/ncx_parser.py
epub_sage/core/organization_analyzer.py
epub_sage/core/structure_parser.py
epub_sage/core/toc_parser.py
epub_sage/extractors/__init__.py
epub_sage/extractors/content_extractor.py
epub_sage/extractors/element_extractors.py
epub_sage/extractors/epub_extractor.py
epub_sage/extractors/epub_validator.py
epub_sage/extractors/html_parser.py
epub_sage/extractors/image_resolver.py
epub_sage/extractors/section_builder.py
epub_sage/extractors/specialized_extractors.py
epub_sage/extractors/toc_content_extractor.py
epub_sage/models/__init__.py
epub_sage/models/dublin_core.py
epub_sage/models/structure.py
epub_sage/processors/__init__.py
epub_sage/processors/content_consolidator.py
epub_sage/processors/helpers.py
epub_sage/processors/orchestrator.py
epub_sage/processors/result.py
epub_sage/services/__init__.py
epub_sage/services/export_service.py
epub_sage/services/search_result.py
epub_sage/services/search_scorer.py
epub_sage/services/search_service.py
epub_sage/utils/__init__.py
epub_sage/utils/calibre_detector.py
epub_sage/utils/statistics.py
epub_sage/utils/text_analyzer.py
epub_sage/utils/xml_namespaces.py
epub_sage/utils/xml_utils.py
epubsage-0.3.0.dist-info/METADATA
epubsage-0.3.0.dist-info/WHEEL
epubsage-0.3.0.dist-info/entry_points.txt
epubsage-0.3.0.dist-info/licenses/LICENSE
epubsage-0.3.0.dist-info/RECORD
