Metadata-Version: 2.4
Name: epubsage
Version: 0.3.0
Summary: A professional EPUB structure and content extraction library with Dublin Core metadata support.
Project-URL: Homepage, https://github.com/Abdullah-Wex/epubsage
Project-URL: Repository, https://github.com/Abdullah-Wex/epubsage
Project-URL: Documentation, https://github.com/Abdullah-Wex/epubsage#readme
Project-URL: Issues, https://github.com/Abdullah-Wex/epubsage/issues
Project-URL: Changelog, https://github.com/Abdullah-Wex/epubsage/blob/main/CHANGELOG.md
Author-email: Abdullah Wex <alshreef15xm@gmail.com>
License: MIT License
License-File: LICENSE
Keywords: dublin-core,ebook,epub,extraction,metadata,parser,reading
Classifier: Development Status :: 4 - Beta
Classifier: Intended Audience :: Developers
Classifier: License :: OSI Approved :: MIT License
Classifier: Operating System :: OS Independent
Classifier: Programming Language :: Python :: 3
Classifier: Programming Language :: Python :: 3.10
Classifier: Programming Language :: Python :: 3.11
Classifier: Programming Language :: Python :: 3.12
Classifier: Programming Language :: Python :: 3.13
Classifier: Topic :: Software Development :: Libraries :: Python Modules
Classifier: Topic :: Text Processing :: Markup
Classifier: Typing :: Typed
Requires-Python: >=3.10
Requires-Dist: beautifulsoup4>=4.12.0
Requires-Dist: lxml>=5.0.0
Requires-Dist: pydantic>=2.0.0
Requires-Dist: typer[all]>=0.12.0
